{"id":"env-config-schema","name":"Environment Config Schema","version":"1.0.0","category":["infra"],"description":"Pydantic-based environment variable configuration with type coercion, validation, and defaults. Single source of truth for app settings across all modules.","input":[".env file or environment variables"],"output":["AppConfig: BaseSettings","config: singleton","is_prod: property"],"tags":["config","environment","settings","pydantic","fastapi","python"],"compatible_with":["Python 3.9+","Pydantic 2.0+"],"used_in_recipes":[],"status":"stable","author":"Tiranyx","license":"MIT"}